{
  "teamId": "ncfc",
  "name": "North Carolina FC",
  "shortName": "NCFC",
  "city": "Cary",
  "sport": "MLS",
  "venue": null,
  "logos": {
    "primary": "https://cdn.sanity.io/images/tqbbtja5/production/6c769b259e15e2cc19206dd44876e0c4ceab9750-64x64.svg",
    "inverted": "",
    "logomark": ""
  },
  "brandColors": {
    "core": "#00416B",
    "dark": "#201400",
    "darkBase": "#111111",
    "darkInteractivePrimary": "#B4A269",
    "darkInteractivePrimaryText": "#000000",
    "darkInteractiveSecondaryText": "#FFFFFF",
    "darkInteractiveTertiaryText": "#B4A269",
    "darkInteractiveTransactional": "#B4A269",
    "darkInteractiveTransactionalText": "#000000",
    "darkNav": "rgba(17, 17, 17, 0.7)",
    "darkSheet": "#292929",
    "darkSurface": "#1F1F1F",
    "displayLetterSpacing": "-0.05em",
    "displaySize100": "18px",
    "displaySize200": "22px",
    "displaySize300": "25px",
    "displaySize400": "32px",
    "displaySize500": "39px",
    "displaySize600": "46px",
    "displaySize700": "54px",
    "displaySize800": "61px",
    "displaySize900": "68px",
    "displayWeight": "900",
    "interactive": "#00416B",
    "inverted": "#B4A269",
    "light": "#B4A269",
    "lightBase": "#FFFFFF",
    "lightInteractivePrimary": "#00416B",
    "lightInteractivePrimaryText": "#FFFFFF",
    "lightInteractiveSecondaryText": "#000000",
    "lightInteractiveTertiaryText": "#00416B",
    "lightInteractiveTransactional": "#00416B",
    "lightInteractiveTransactionalText": "#FFFFFF",
    "lightNav": "rgba(255, 255, 255, 0.75)",
    "lightSheet": "#FFFFFF",
    "lightSurface": "#F4F4F4"
  },
  "buttonRadius": "100px",
  "displayFont": "Public Caps Pro",
  "vfsFar": null,
  "vfsClose": null,
  "urls": {}
}